regenbib/__init__.py
regenbib/cli_import.py
regenbib/cli_render.py
regenbib/store.py
regenbib-0.0.5.dist-info/entry_points.txt
regenbib-0.0.5.dist-info/WHEEL
regenbib-0.0.5.dist-info/METADATA
regenbib-0.0.5.dist-info/LICENSE
regenbib-0.0.5.dist-info/RECORD
