Metadata-Version: 2.1
Name: regenbib
Version: 0.0.5
Summary: (Re-)generate tidy .bib files from online sources
Home-page: https://github.com/joachimneu/regenbib
License: GPL-3.0-only
Keywords: latex,bibtex,biblatex
Author: Joachim Neu
Author-email: jneu@stanford.edu
Requires-Python: >=3.10,<4.0
Classifier: License :: OSI Approved :: GNU General Public License v3 (GPLv3)
Classifier: Programming Language :: Python :: 3
Classifier: Programming Language :: Python :: 3.10
Classifier: Programming Language :: Python :: 3.11
Requires-Dist: arxiv (>=1.4.7,<2.0.0)
Requires-Dist: beautifulsoup4 (>=4.12.2,<5.0.0)
Requires-Dist: bibtex-dblp (>=0.9,<0.10)
Requires-Dist: marshmallow-dataclass[enum,union] (==8.5.14)
Requires-Dist: requests (>=2.29.0,<3.0.0)
Project-URL: Documentation, https://github.com/joachimneu/regenbib
Project-URL: Repository, https://github.com/joachimneu/regenbib
